{
  "annotations": {
    "list": [
      {
        "builtIn": 1,
        "datasource": {
          "type": "datasource",
          "uid": "grafana"
        },
        "enable": true,
        "hide": true,
        "iconColor": "rgba(0, 211, 255, 1)",
        "name": "Annotations & Alerts",
        "target": {
          "limit": 100,
          "matchAny": false,
          "tags": [],
          "type": "dashboard"
        },
        "type": "dashboard"
      }
    ]
  },
  "editable": true,
  "fiscalYearStartMonth": 0,
  "graphTooltip": 0,
  "id": 5,
  "links": [],
  "liveNow": false,
  "panels": [
    {
      "collapsed": true,
      "gridPos": {
        "h": 1,
        "w": 24,
        "x": 0,
        "y": 0
      },
      "id": 55,
      "panels": [
        {
          "datasource": {
            "type": "prometheus",
            "uid": "PBFA97CFB590B2093"
          },
          "fieldConfig": {
            "defaults": {
              "color": {
                "mode": "palette-classic"
              },
              "custom": {
                "axisCenteredZero": false,
                "axisColorMode": "text",
                "axisLabel": "",
                "axisPlacement": "auto",
                "barAlignment": 0,
                "drawStyle": "line",
                "fillOpacity": 0,
                "gradientMode": "none",
                "hideFrom": {
                  "legend": false,
                  "tooltip": false,
                  "viz": false
                },
                "lineInterpolation": "linear",
                "lineWidth": 1,
                "pointSize": 5,
                "scaleDistribution": {
                  "type": "linear"
                },
                "showPoints": "auto",
                "spanNulls": false,
                "stacking": {
                  "group": "A",
                  "mode": "none"
                },
                "thresholdsStyle": {
                  "mode": "off"
                }
              },
              "mappings": [],
              "thresholds": {
                "mode": "absolute",
                "steps": [
                  {
                    "color": "green"
                  },
                  {
                    "color": "red",
                    "value": 80
                  }
                ]
              }
            },
            "overrides": []
          },
          "gridPos": {
            "h": 8,
            "w": 12,
            "x": 0,
            "y": 25
          },
          "id": 53,
          "options": {
            "legend": {
              "calcs": [],
              "displayMode": "list",
              "placement": "bottom",
              "showLegend": true
            },
            "tooltip": {
              "mode": "single",
              "sort": "none"
            }
          },
          "targets": [
            {
              "datasource": {
                "type": "prometheus",
                "uid": "PBFA97CFB590B2093"
              },
              "refId": "A"
            }
          ],
          "title": "Issuance rate per node",
          "type": "timeseries"
        }
      ],
      "title": "Processing, BPS",
      "type": "row"
    },
    {
      "collapsed": false,
      "gridPos": {
        "h": 1,
        "w": 24,
        "x": 0,
        "y": 1
      },
      "id": 63,
      "panels": [],
      "title": "Epoch metrics",
      "type": "row"
    },
    {
      "datasource": {
        "type": "prometheus",
        "uid": "PBFA97CFB590B2093"
      },
      "fieldConfig": {
        "defaults": {
          "color": {
            "fixedColor": "semi-dark-blue",
            "mode": "fixed"
          },
          "custom": {
            "axisCenteredZero": false,
            "axisColorMode": "text",
            "axisLabel": "",
            "axisPlacement": "auto",
            "fillOpacity": 41,
            "gradientMode": "none",
            "hideFrom": {
              "legend": false,
              "tooltip": false,
              "viz": false
            },
            "lineWidth": 1,
            "scaleDistribution": {
              "type": "linear"
            }
          },
          "mappings": [],
          "thresholds": {
            "mode": "absolute",
            "steps": [
              {
                "color": "semi-dark-blue",
                "value": null
              }
            ]
          }
        },
        "overrides": [
          {
            "matcher": {
              "id": "byName",
              "options": "Epoch Index"
            },
            "properties": [
              {
                "id": "unit",
                "value": "EI"
              }
            ]
          }
        ]
      },
      "gridPos": {
        "h": 6,
        "w": 24,
        "x": 0,
        "y": 2
      },
      "id": 107,
      "options": {
        "barRadius": 0,
        "barWidth": 0.97,
        "colorByField": "instance",
        "groupWidth": 0.7,
        "legend": {
          "calcs": [],
          "displayMode": "list",
          "placement": "bottom",
          "showLegend": false
        },
        "orientation": "auto",
        "showValue": "always",
        "stacking": "none",
        "text": {
          "valueSize": 40
        },
        "tooltip": {
          "mode": "single",
          "sort": "none"
        },
        "xTickLabelRotation": 0,
        "xTickLabelSpacing": 200
      },
      "pluginVersion": "9.2.4",
      "targets": [
        {
          "datasource": {
            "type": "prometheus",
            "uid": "PBFA97CFB590B2093"
          },
          "editorMode": "code",
          "exemplar": false,
          "expr": "max(last_commitment{}) by (epoch, instance)",
          "format": "table",
          "instant": true,
          "legendFormat": "__auto",
          "range": false,
          "refId": "A"
        }
      ],
      "title": "Last commitmed epoch",
      "transformations": [
        {
          "id": "convertFieldType",
          "options": {
            "conversions": [
              {
                "destinationType": "number",
                "targetField": "epoch"
              }
            ],
            "fields": {}
          }
        },
        {
          "id": "groupBy",
          "options": {
            "fields": {
              "Value": {
                "aggregations": [
                  "max"
                ]
              },
              "epoch": {
                "aggregations": [
                  "max"
                ],
                "operation": "aggregate"
              },
              "instance": {
                "aggregations": [],
                "operation": "groupby"
              }
            }
          }
        },
        {
          "id": "organize",
          "options": {
            "excludeByName": {},
            "indexByName": {},
            "renameByName": {
              "epoch (lastNotNull)": "Epoch Index"
            }
          }
        }
      ],
      "type": "barchart"
    },
    {
      "datasource": {
        "type": "prometheus",
        "uid": "PBFA97CFB590B2093"
      },
      "description": "",
      "fieldConfig": {
        "defaults": {
          "color": {
            "fixedColor": "semi-dark-orange",
            "mode": "fixed"
          },
          "custom": {
            "axisCenteredZero": false,
            "axisColorMode": "text",
            "axisLabel": "",
            "axisPlacement": "auto",
            "fillOpacity": 41,
            "gradientMode": "none",
            "hideFrom": {
              "legend": false,
              "tooltip": false,
              "viz": false
            },
            "lineWidth": 1,
            "scaleDistribution": {
              "type": "linear"
            }
          },
          "mappings": [],
          "thresholds": {
            "mode": "absolute",
            "steps": [
              {
                "color": "semi-dark-blue",
                "value": null
              }
            ]
          }
        },
        "overrides": [
          {
            "matcher": {
              "id": "byName",
              "options": "Epoch Index"
            },
            "properties": [
              {
                "id": "unit",
                "value": "EI"
              }
            ]
          }
        ]
      },
      "gridPos": {
        "h": 6,
        "w": 24,
        "x": 0,
        "y": 8
      },
      "id": 96,
      "options": {
        "barRadius": 0,
        "barWidth": 0.97,
        "colorByField": "instance",
        "groupWidth": 0.7,
        "legend": {
          "calcs": [],
          "displayMode": "list",
          "placement": "bottom",
          "showLegend": false
        },
        "orientation": "auto",
        "showValue": "always",
        "stacking": "none",
        "text": {
          "valueSize": 40
        },
        "tooltip": {
          "mode": "single",
          "sort": "none"
        },
        "xTickLabelRotation": 0,
        "xTickLabelSpacing": 200
      },
      "pluginVersion": "9.2.4",
      "targets": [
        {
          "datasource": {
            "type": "prometheus",
            "uid": "PBFA97CFB590B2093"
          },
          "editorMode": "code",
          "exemplar": false,
          "expr": "max(last_commitment{}) by (epoch, instance)",
          "format": "table",
          "instant": true,
          "legendFormat": "__auto",
          "range": false,
          "refId": "A"
        }
      ],
      "title": "Last confirmed epoch",
      "transformations": [
        {
          "id": "convertFieldType",
          "options": {
            "conversions": [
              {
                "destinationType": "number",
                "targetField": "epoch"
              }
            ],
            "fields": {}
          }
        },
        {
          "id": "groupBy",
          "options": {
            "fields": {
              "Value": {
                "aggregations": [
                  "max"
                ]
              },
              "epoch": {
                "aggregations": [
                  "max"
                ],
                "operation": "aggregate"
              },
              "instance": {
                "aggregations": [],
                "operation": "groupby"
              }
            }
          }
        },
        {
          "id": "organize",
          "options": {
            "excludeByName": {},
            "indexByName": {},
            "renameByName": {
              "epoch (lastNotNull)": "Epoch Index"
            }
          }
        }
      ],
      "type": "barchart"
    },
    {
      "datasource": {
        "type": "prometheus",
        "uid": "PBFA97CFB590B2093"
      },
      "fieldConfig": {
        "defaults": {
          "color": {
            "mode": "continuous-YlBl"
          },
          "custom": {
            "axisCenteredZero": false,
            "axisColorMode": "text",
            "axisLabel": "",
            "axisPlacement": "auto",
            "fillOpacity": 72,
            "gradientMode": "none",
            "hideFrom": {
              "legend": false,
              "tooltip": false,
              "viz": false
            },
            "lineWidth": 1,
            "scaleDistribution": {
              "type": "linear"
            }
          },
          "mappings": [],
          "thresholds": {
            "mode": "absolute",
            "steps": [
              {
                "color": "green",
                "value": null
              }
            ]
          }
        },
        "overrides": [
          {
            "matcher": {
              "id": "byName",
              "options": "instance"
            },
            "properties": [
              {
                "id": "color",
                "value": {
                  "mode": "palette-classic"
                }
              }
            ]
          },
          {
            "matcher": {
              "id": "byName",
              "options": "epoch"
            },
            "properties": [
              {
                "id": "unit",
                "value": "EI"
              }
            ]
          }
        ]
      },
      "gridPos": {
        "h": 8,
        "w": 12,
        "x": 0,
        "y": 14
      },
      "id": 67,
      "options": {
        "barRadius": 0,
        "barWidth": 0.93,
        "colorByField": "Accepted blocks",
        "groupWidth": 0.7,
        "legend": {
          "calcs": [],
          "displayMode": "list",
          "placement": "bottom",
          "showLegend": false
        },
        "orientation": "auto",
        "showValue": "auto",
        "stacking": "none",
        "text": {},
        "tooltip": {
          "mode": "single",
          "sort": "none"
        },
        "xField": "epoch",
        "xTickLabelMaxLength": 12,
        "xTickLabelRotation": -45,
        "xTickLabelSpacing": 0
      },
      "repeat": "instance",
      "repeatDirection": "v",
      "targets": [
        {
          "datasource": {
            "type": "prometheus",
            "uid": "PBFA97CFB590B2093"
          },
          "editorMode": "code",
          "exemplar": false,
          "expr": "accepted_blks_of_epoch{instance=\"$instance\"}",
          "format": "table",
          "instant": true,
          "legendFormat": "{{epoch}}, {{instance}}",
          "range": false,
          "refId": "A"
        }
      ],
      "title": "Blocks accepted per epoch $instance",
      "transformations": [
        {
          "id": "organize",
          "options": {
            "excludeByName": {
              "Time": true,
              "__name__": true,
              "epoch": false,
              "job": true
            },
            "indexByName": {
              "Time": 0,
              "Value": 3,
              "__name__": 1,
              "epoch": 2,
              "instance": 4,
              "job": 5
            },
            "renameByName": {
              "Value": "Accepted blocks"
            }
          }
        },
        {
          "id": "convertFieldType",
          "options": {
            "conversions": [
              {
                "destinationType": "number",
                "targetField": "epoch"
              }
            ],
            "fields": {}
          }
        },
        {
          "id": "sortBy",
          "options": {
            "fields": {},
            "sort": [
              {
                "desc": true,
                "field": "epoch"
              }
            ]
          }
        },
        {
          "id": "limit",
          "options": {
            "limitField": 15
          }
        },
        {
          "id": "sortBy",
          "options": {
            "fields": {},
            "sort": [
              {
                "field": "epoch"
              }
            ]
          }
        }
      ],
      "type": "barchart"
    },
    {
      "datasource": {
        "type": "prometheus",
        "uid": "PBFA97CFB590B2093"
      },
      "description": "Orphaned blocks",
      "fieldConfig": {
        "defaults": {
          "color": {
            "mode": "continuous-GrYlRd"
          },
          "custom": {
            "axisCenteredZero": false,
            "axisColorMode": "text",
            "axisLabel": "",
            "axisPlacement": "auto",
            "fillOpacity": 80,
            "gradientMode": "none",
            "hideFrom": {
              "legend": false,
              "tooltip": false,
              "viz": false
            },
            "lineWidth": 1,
            "scaleDistribution": {
              "type": "linear"
            }
          },
          "mappings": [],
          "thresholds": {
            "mode": "absolute",
            "steps": [
              {
                "color": "green",
                "value": null
              },
              {
                "color": "red",
                "value": 80
              }
            ]
          }
        },
        "overrides": [
          {
            "matcher": {
              "id": "byName",
              "options": "epoch"
            },
            "properties": [
              {
                "id": "unit",
                "value": "EI"
              }
            ]
          }
        ]
      },
      "gridPos": {
        "h": 8,
        "w": 12,
        "x": 12,
        "y": 14
      },
      "id": 75,
      "interval": "30s",
      "options": {
        "barRadius": 0,
        "barWidth": 0.97,
        "colorByField": "Blocks orphaned",
        "groupWidth": 0.7,
        "legend": {
          "calcs": [],
          "displayMode": "list",
          "placement": "bottom",
          "showLegend": false
        },
        "orientation": "auto",
        "showValue": "auto",
        "stacking": "none",
        "tooltip": {
          "mode": "single",
          "sort": "none"
        },
        "xField": "epoch",
        "xTickLabelRotation": -45,
        "xTickLabelSpacing": 0
      },
      "repeat": "instance",
      "repeatDirection": "v",
      "targets": [
        {
          "datasource": {
            "type": "prometheus",
            "uid": "PBFA97CFB590B2093"
          },
          "editorMode": "code",
          "expr": "blk_removed_from_epoch{instance=\"$instance\"}",
          "format": "table",
          "interval": "",
          "legendFormat": "__auto",
          "range": true,
          "refId": "A"
        }
      ],
      "title": "Blocks removed per epoch",
      "transformations": [
        {
          "id": "convertFieldType",
          "options": {
            "conversions": [
              {
                "destinationType": "number",
                "targetField": "epoch"
              }
            ],
            "fields": {}
          }
        },
        {
          "id": "organize",
          "options": {
            "excludeByName": {
              "Time": true,
              "__name__": true,
              "job": true
            },
            "indexByName": {},
            "renameByName": {
              "Value": "Blocks orphaned"
            }
          }
        },
        {
          "id": "sortBy",
          "options": {
            "fields": {},
            "sort": [
              {
                "desc": true,
                "field": "epoch"
              }
            ]
          }
        },
        {
          "id": "limit",
          "options": {
            "limitField": 15
          }
        },
        {
          "id": "sortBy",
          "options": {
            "fields": {},
            "sort": [
              {
                "field": "epoch"
              }
            ]
          }
        }
      ],
      "type": "barchart"
    },
    {
      "collapsed": false,
      "gridPos": {
        "h": 1,
        "w": 24,
        "x": 0,
        "y": 38
      },
      "id": 33,
      "panels": [],
      "title": "Epoch Commitments",
      "type": "row"
    },
    {
      "datasource": {
        "type": "prometheus",
        "uid": "PBFA97CFB590B2093"
      },
      "fieldConfig": {
        "defaults": {
          "color": {
            "mode": "fixed"
          },
          "custom": {
            "align": "auto",
            "displayMode": "auto",
            "filterable": false,
            "inspect": false
          },
          "mappings": [],
          "thresholds": {
            "mode": "absolute",
            "steps": [
              {
                "color": "semi-dark-green",
                "value": null
              }
            ]
          },
          "unit": "EI"
        },
        "overrides": [
          {
            "matcher": {
              "id": "byName",
              "options": "epoch"
            },
            "properties": [
              {
                "id": "custom.displayMode",
                "value": "color-text"
              },
              {
                "id": "color",
                "value": {
                  "fixedColor": "dark-green",
                  "mode": "fixed"
                }
              }
            ]
          },
          {
            "matcher": {
              "id": "byName",
              "options": "Value"
            },
            "properties": [
              {
                "id": "custom.hidden",
                "value": true
              }
            ]
          },
          {
            "matcher": {
              "id": "byName",
              "options": "commitment"
            },
            "properties": [
              {
                "id": "custom.displayMode",
                "value": "color-background-solid"
              },
              {
                "id": "color",
                "value": {
                  "fixedColor": "#143003",
                  "mode": "fixed"
                }
              }
            ]
          }
        ]
      },
      "gridPos": {
        "h": 8,
        "w": 8,
        "x": 0,
        "y": 39
      },
      "id": 39,
      "maxPerRow": 4,
      "options": {
        "footer": {
          "enablePagination": false,
          "fields": "",
          "reducer": [
            "last"
          ],
          "show": false
        },
        "showHeader": true,
        "sortBy": [
          {
            "desc": true,
            "displayName": "Epoch Index"
          }
        ]
      },
      "pluginVersion": "9.2.4",
      "repeat": "instance",
      "repeatDirection": "h",
      "targets": [
        {
          "datasource": {
            "type": "prometheus",
            "uid": "PBFA97CFB590B2093"
          },
          "editorMode": "code",
          "exemplar": false,
          "expr": "max(last_commitment{instance=\"$instance\", epoch!=\"0\"}) by (commitment, epoch)",
          "format": "table",
          "hide": false,
          "instant": true,
          "legendFormat": "__auto",
          "range": false,
          "refId": "A"
        }
      ],
      "title": "Commitments $instance",
      "transformations": [
        {
          "id": "seriesToRows",
          "options": {}
        },
        {
          "id": "convertFieldType",
          "options": {
            "conversions": [
              {
                "destinationType": "number",
                "targetField": "epoch"
              }
            ],
            "fields": {}
          }
        },
        {
          "id": "limit",
          "options": {
            "limitField": 100
          }
        },
        {
          "id": "organize",
          "options": {
            "excludeByName": {
              "Time": true,
              "Value": true
            },
            "indexByName": {},
            "renameByName": {
              "commitment": "Commitment",
              "epoch": "Epoch Index"
            }
          }
        }
      ],
      "transparent": true,
      "type": "table"
    },
    {
      "datasource": {
        "type": "prometheus",
        "uid": "PBFA97CFB590B2093"
      },
      "fieldConfig": {
        "defaults": {
          "color": {
            "mode": "palette-classic"
          },
          "custom": {
            "axisCenteredZero": false,
            "axisColorMode": "text",
            "axisLabel": "",
            "axisPlacement": "auto",
            "fillOpacity": 80,
            "gradientMode": "none",
            "hideFrom": {
              "legend": false,
              "tooltip": false,
              "viz": false
            },
            "lineWidth": 4,
            "scaleDistribution": {
              "type": "linear"
            }
          },
          "mappings": [],
          "thresholds": {
            "mode": "absolute",
            "steps": [
              {
                "color": "green",
                "value": null
              },
              {
                "color": "red",
                "value": 80
              }
            ]
          }
        },
        "overrides": []
      },
      "gridPos": {
        "h": 6,
        "w": 12,
        "x": 0,
        "y": 47
      },
      "id": 47,
      "options": {
        "barRadius": 0.05,
        "barWidth": 0.97,
        "colorByField": "Metric",
        "groupWidth": 0.7,
        "legend": {
          "calcs": [],
          "displayMode": "table",
          "placement": "right",
          "showLegend": false
        },
        "orientation": "auto",
        "showValue": "always",
        "stacking": "none",
        "tooltip": {
          "mode": "single",
          "sort": "none"
        },
        "xTickLabelRotation": 0,
        "xTickLabelSpacing": 0
      },
      "targets": [
        {
          "datasource": {
            "type": "prometheus",
            "uid": "PBFA97CFB590B2093"
          },
          "editorMode": "code",
          "exemplar": false,
          "expr": "number_of_seen_other_commitments{instance=~\"$instance\"}",
          "format": "time_series",
          "instant": false,
          "legendFormat": "{{instance}}",
          "range": true,
          "refId": "A"
        }
      ],
      "title": "Number of forks noticed by node",
      "transformations": [
        {
          "id": "limit",
          "options": {
            "limitField": 1
          }
        },
        {
          "id": "seriesToRows",
          "options": {}
        }
      ],
      "type": "barchart"
    },
    {
      "collapsed": false,
      "gridPos": {
        "h": 1,
        "w": 24,
        "x": 0,
        "y": 53
      },
      "id": 59,
      "panels": [],
      "title": "Missing commitments",
      "type": "row"
    },
    {
      "datasource": {
        "type": "prometheus",
        "uid": "PBFA97CFB590B2093"
      },
      "fieldConfig": {
        "defaults": {
          "color": {
            "mode": "palette-classic"
          },
          "custom": {
            "axisCenteredZero": false,
            "axisColorMode": "text",
            "axisLabel": "",
            "axisPlacement": "auto",
            "fillOpacity": 80,
            "gradientMode": "none",
            "hideFrom": {
              "legend": false,
              "tooltip": false,
              "viz": false
            },
            "lineWidth": 4,
            "scaleDistribution": {
              "type": "linear"
            }
          },
          "mappings": [],
          "thresholds": {
            "mode": "absolute",
            "steps": [
              {
                "color": "green",
                "value": null
              },
              {
                "color": "red",
                "value": 80
              }
            ]
          }
        },
        "overrides": []
      },
      "gridPos": {
        "h": 6,
        "w": 12,
        "x": 0,
        "y": 54
      },
      "id": 49,
      "options": {
        "barRadius": 0.05,
        "barWidth": 0.97,
        "groupWidth": 0.7,
        "legend": {
          "calcs": [],
          "displayMode": "table",
          "placement": "right",
          "showLegend": false
        },
        "orientation": "auto",
        "showValue": "auto",
        "stacking": "none",
        "tooltip": {
          "mode": "single",
          "sort": "none"
        },
        "xTickLabelRotation": 0,
        "xTickLabelSpacing": 0
      },
      "targets": [
        {
          "datasource": {
            "type": "prometheus",
            "uid": "PBFA97CFB590B2093"
          },
          "editorMode": "code",
          "exemplar": false,
          "expr": "missing_commitments_received{instance=~\"$instance\"}",
          "format": "time_series",
          "instant": false,
          "legendFormat": "{{instance}}",
          "range": true,
          "refId": "A"
        }
      ],
      "title": "Number of received missing commitments ",
      "transformations": [
        {
          "id": "limit",
          "options": {
            "limitField": 1
          }
        },
        {
          "id": "seriesToRows",
          "options": {}
        }
      ],
      "type": "barchart"
    },
    {
      "datasource": {
        "type": "prometheus",
        "uid": "PBFA97CFB590B2093"
      },
      "fieldConfig": {
        "defaults": {
          "color": {
            "mode": "palette-classic"
          },
          "custom": {
            "axisCenteredZero": false,
            "axisColorMode": "text",
            "axisGridShow": true,
            "axisLabel": "",
            "axisPlacement": "auto",
            "fillOpacity": 80,
            "gradientMode": "none",
            "hideFrom": {
              "legend": false,
              "tooltip": false,
              "viz": false
            },
            "lineWidth": 4,
            "scaleDistribution": {
              "type": "linear"
            }
          },
          "mappings": [],
          "thresholds": {
            "mode": "absolute",
            "steps": [
              {
                "color": "green",
                "value": null
              },
              {
                "color": "red",
                "value": 80
              }
            ]
          }
        },
        "overrides": []
      },
      "gridPos": {
        "h": 6,
        "w": 12,
        "x": 12,
        "y": 54
      },
      "id": 48,
      "options": {
        "barRadius": 0.05,
        "barWidth": 0.97,
        "groupWidth": 0.7,
        "legend": {
          "calcs": [],
          "displayMode": "table",
          "placement": "right",
          "showLegend": false
        },
        "orientation": "auto",
        "showValue": "auto",
        "stacking": "none",
        "text": {
          "valueSize": 20
        },
        "tooltip": {
          "mode": "single",
          "sort": "none"
        },
        "xField": "Metric",
        "xTickLabelRotation": 0,
        "xTickLabelSpacing": 0
      },
      "targets": [
        {
          "datasource": {
            "type": "prometheus",
            "uid": "PBFA97CFB590B2093"
          },
          "editorMode": "code",
          "exemplar": false,
          "expr": "missing_commitments_requested{instance=~\"$instance\"}",
          "format": "time_series",
          "instant": false,
          "legendFormat": "{{instance}}",
          "range": true,
          "refId": "A"
        }
      ],
      "title": "Number of missing commitments by node",
      "transformations": [
        {
          "id": "limit",
          "options": {
            "limitField": 1
          }
        },
        {
          "id": "seriesToRows",
          "options": {}
        }
      ],
      "type": "barchart"
    }
  ],
  "refresh": "5s",
  "schemaVersion": 37,
  "style": "dark",
  "tags": [],
  "templating": {
    "list": [
      {
        "current": {
          "selected": true,
          "text": [
            "All"
          ],
          "value": [
            "$__all"
          ]
        },
        "datasource": {
          "type": "prometheus",
          "uid": "PBFA97CFB590B2093"
        },
        "definition": "label_values(iota_info_app, instance)",
        "hide": 0,
        "includeAll": true,
        "label": "Instance",
        "multi": true,
        "name": "instance",
        "options": [],
        "query": {
          "query": "label_values(iota_info_app, instance)",
          "refId": "StandardVariableQuery"
        },
        "refresh": 1,
        "regex": "",
        "skipUrlSync": false,
        "sort": 0,
        "type": "query"
      },
      {
        "datasource": {
          "type": "prometheus",
          "uid": "PBFA97CFB590B2093"
        },
        "filters": [],
        "hide": 0,
        "name": "Filters",
        "skipUrlSync": false,
        "type": "adhoc"
      }
    ]
  },
  "time": {
    "from": "now-15m",
    "to": "now"
  },
  "timepicker": {
    "refresh_intervals": [
      "5s",
      "10s",
      "30s",
      "1m",
      "5m",
      "15m",
      "30m",
      "1h",
      "2h",
      "1d"
    ]
  },
  "timezone": "",
  "title": "Global nodes view",
  "uid": "JKcc02v4k",
  "version": 5,
  "weekStart": ""
}